[
  {
    "description": "    As a user\n    I want to access the dashboard page\n    So that I can view my account information and data",
    "keyword": "Feature",
    "name": "Dashboard Page Functionality",
    "line": 1,
    "id": "dashboard-page-functionality",
    "tags": [],
    "uri": "Dashboard.feature",
    "elements": [
      {
        "id": "dashboard-page-functionality;adding,update,add-more-filter,-clear-filter-and-search,view-details-and-delete-new-buildings",
        "keyword": "Scenario",
        "line": 25,
        "name": "Adding,Update,add more filter, Clear filter and Search,View Details and Delete new Buildings",
        "tags": [],
        "type": "scenario",
        "steps": [
          {
            "arguments": [],
            "keyword": "Given ",
            "line": 7,
            "name": "I should navigate to application",
            "result": {
              "status": "passed",
              "duration": 8829000000
            }
          },
          {
            "arguments": [],
            "keyword": "When ",
            "line": 8,
            "name": "I should Sign In into the application",
            "result": {
              "status": "passed",
              "duration": 9149000000
            }
          },
          {
            "arguments": [],
            "keyword": "Then ",
            "line": 9,
            "name": "Close the terms of service window",
            "result": {
              "status": "passed",
              "duration": 15287000000
            }
          },
          {
            "arguments": [],
            "keyword": "Then ",
            "line": 26,
            "name": "I should be redirected to the dashboard page",
            "result": {
              "status": "passed",
              "duration": 72000000
            }
          },
          {
            "arguments": [],
            "keyword": "And ",
            "line": 27,
            "name": "Click on Buildings Tab",
            "result": {
              "status": "passed",
              "duration": 2069000000
            }
          },
          {
            "arguments": [],
            "keyword": "Then ",
            "line": 28,
            "name": "I should click on Add building button",
            "result": {
              "status": "passed",
              "duration": 1661000000
            }
          },
          {
            "arguments": [],
            "keyword": "And ",
            "line": 29,
            "name": "I should Enter Building Name,Phone and Extension",
            "result": {
              "status": "passed",
              "duration": 918000000
            }
          },
          {
            "arguments": [],
            "keyword": "Then ",
            "line": 30,
            "name": "I should Enter Building Abbreviation and Select Default building",
            "result": {
              "status": "passed",
              "duration": 381000000
            }
          },
          {
            "arguments": [],
            "keyword": "And ",
            "line": 31,
            "name": "Enter Billing Id, Shipping Address and select from dropdown",
            "result": {
              "status": "passed",
              "duration": 3606000000
            }
          },
          {
            "arguments": [],
            "keyword": "Then ",
            "line": 32,
            "name": "Click on checkbox Same as Shipping Address",
            "result": {
              "status": "passed",
              "duration": 3093000000
            }
          },
          {
            "arguments": [],
            "keyword": "And ",
            "line": 33,
            "name": "Click on save button",
            "result": {
              "status": "passed",
              "duration": 62000000
            }
          },
          {
            "arguments": [],
            "keyword": "Then ",
            "line": 34,
            "name": "Verify the builing details added in table",
            "result": {
              "status": "passed",
              "duration": 2039000000
            }
          },
          {
            "arguments": [],
            "keyword": "And ",
            "line": 53,
            "name": "Click on Buildings Tab",
            "result": {
              "status": "passed",
              "duration": 2107000000
            }
          },
          {
            "arguments": [],
            "keyword": "And ",
            "line": 54,
            "name": "Click on Edit Icon of builing",
            "result": {
              "status": "passed",
              "duration": 3766000000
            }
          },
          {
            "arguments": [],
            "keyword": "And ",
            "line": 55,
            "name": "I should edit Building Name,Phone and Extension of builing",
            "result": {
              "status": "passed",
              "duration": 1277000000
            }
          },
          {
            "arguments": [],
            "keyword": "Then ",
            "line": 56,
            "name": "I should edit Select Default building",
            "result": {
              "status": "passed",
              "duration": 67000000
            }
          },
          {
            "arguments": [],
            "keyword": "Then ",
            "line": 57,
            "name": "Click on update button of builing",
            "result": {
              "status": "passed",
              "duration": 64000000
            }
          },
          {
            "arguments": [],
            "keyword": "And ",
            "line": 58,
            "name": "Verify the Record has been updated Meassage of builing",
            "result": {
              "status": "passed",
              "duration": 472000000
            }
          },
          {
            "arguments": [],
            "keyword": "And ",
            "line": 59,
            "name": "Click on Delete Icon of building",
            "result": {
              "status": "passed",
              "duration": 4742000000
            }
          },
          {
            "arguments": [],
            "keyword": "Then ",
            "line": 60,
            "name": "Click on Confirm Delete button of building",
            "result": {
              "status": "passed",
              "duration": 84000000
            }
          },
          {
            "arguments": [],
            "keyword": "And ",
            "line": 61,
            "name": "Verify the record is deleted successfully of building",
            "result": {
              "status": "passed",
              "duration": 497000000
            }
          }
        ]
      }
    ]
  }
]