[
  {
    "description": "    As a user\n    I want to access the dashboard page\n    So that I can view my account information and data",
    "keyword": "Feature",
    "name": "LoanerManagement Page Functionality",
    "line": 1,
    "id": "loanermanagement-page-functionality",
    "tags": [],
    "uri": "LoanerManagement.feature",
    "elements": [
      {
        "id": "loanermanagement-page-functionality;visiblity-and-add,-remove-loaner-pool-of-loanermanagement-page",
        "keyword": "Scenario",
        "line": 13,
        "name": "Visiblity and add, remove loaner pool of LoanerManagement page",
        "tags": [],
        "type": "scenario",
        "steps": [
          {
            "arguments": [],
            "keyword": "Given ",
            "line": 7,
            "name": "I should navigate to application",
            "result": {
              "status": "passed",
              "duration": 3059000000
            }
          },
          {
            "arguments": [],
            "keyword": "When ",
            "line": 8,
            "name": "I should Sign In into the application",
            "result": {
              "status": "passed",
              "duration": 5655000000
            }
          },
          {
            "arguments": [],
            "keyword": "Then ",
            "line": 9,
            "name": "close the terms of service window",
            "result": {
              "status": "passed",
              "duration": 9079000000
            }
          },
          {
            "arguments": [],
            "keyword": "Then ",
            "line": 10,
            "name": "Click on Manage Devices",
            "result": {
              "status": "passed",
              "duration": 82000000
            }
          },
          {
            "arguments": [],
            "keyword": "And ",
            "line": 11,
            "name": "Click on LoanerManagement Tab",
            "result": {
              "status": "passed",
              "duration": 538000000
            }
          },
          {
            "arguments": [],
            "keyword": "And ",
            "line": 14,
            "name": "Table for LoanerManagement should be visible",
            "result": {
              "status": "passed",
              "duration": 9000000
            }
          },
          {
            "arguments": [],
            "keyword": "Then ",
            "line": 15,
            "name": "Search the serial no in search box of Available Devices section",
            "result": {
              "status": "passed",
              "duration": 3624000000
            }
          },
          {
            "arguments": [],
            "keyword": "And ",
            "line": 16,
            "name": "Verify the search result",
            "result": {
              "status": "passed",
              "duration": 26000000
            }
          },
          {
            "arguments": [],
            "keyword": "Then ",
            "line": 17,
            "name": "Click on the Add to loaner pool",
            "result": {
              "status": "passed",
              "duration": 82000000
            }
          },
          {
            "arguments": [],
            "keyword": "Then ",
            "line": 18,
            "name": "Search the serial no in the Available section",
            "result": {
              "status": "failed",
              "duration": 7793000000,
              "error_message": "AssertionError: Timed out retrying after 4000ms: Expected to find element: `2`, but never found it. Queried from:\n\n              > cy.get(.css-1xz8d5v, [object Object]).eq(0).find(tbody tr).eq(0).find(td)\n    at LoanerManagementActions.verifySearchAvailable (cypress/integration/PageObject/PageActions/LoanerManagementActions.js:41:74)\n    at Context.eval (cypress/integration/LoanerManagement/LoanerManagement.spec.js:38:9)\n    at Context.resolveAndRunStepDefinition (node_modules/cypress-cucumber-preprocessor/lib/resolveStepDefinition.js:193:0)\n    at Context.eval (node_modules/cypress-cucumber-preprocessor/lib/createTestFromScenario.js:27:0)"
            }
          },
          {
            "arguments": [],
            "keyword": "And ",
            "line": 19,
            "name": "Click on th add Student button",
            "result": {
              "status": "skipped"
            }
          },
          {
            "arguments": [],
            "keyword": "Then ",
            "line": 20,
            "name": "Enter Fullname, title and email",
            "result": {
              "status": "skipped"
            }
          },
          {
            "arguments": [],
            "keyword": "And ",
            "line": 21,
            "name": "Select status, building and student_id",
            "result": {
              "status": "skipped"
            }
          },
          {
            "arguments": [],
            "keyword": "Then ",
            "line": 22,
            "name": "Click on the submit button of form",
            "result": {
              "status": "skipped"
            }
          },
          {
            "arguments": [],
            "keyword": "And ",
            "line": 23,
            "name": "Verify the student added successfully",
            "result": {
              "status": "skipped"
            }
          },
          {
            "arguments": [],
            "keyword": "Then ",
            "line": 24,
            "name": "Click on check out button",
            "result": {
              "status": "skipped"
            }
          },
          {
            "arguments": [],
            "keyword": "And ",
            "line": 25,
            "name": "Select the student name",
            "result": {
              "status": "skipped"
            }
          },
          {
            "arguments": [],
            "keyword": "Then ",
            "line": 26,
            "name": "Click on the submit button",
            "result": {
              "status": "skipped"
            }
          },
          {
            "arguments": [],
            "keyword": "And ",
            "line": 27,
            "name": "Search the serial no in the check out section",
            "result": {
              "status": "skipped"
            }
          },
          {
            "arguments": [],
            "keyword": "Then ",
            "line": 28,
            "name": "Click on the Check in button",
            "result": {
              "status": "skipped"
            }
          },
          {
            "arguments": [],
            "keyword": "And ",
            "line": 29,
            "name": "Enter note and click on submit button",
            "result": {
              "status": "skipped"
            }
          },
          {
            "arguments": [],
            "keyword": "Then ",
            "line": 30,
            "name": "Verify the device is added in Available section",
            "result": {
              "status": "skipped"
            }
          },
          {
            "arguments": [],
            "keyword": "And ",
            "line": 31,
            "name": "Click on remove from loaner pool button",
            "result": {
              "status": "skipped"
            }
          }
        ]
      }
    ]
  }
]