[
  {
    "description": "    As a user\n    I want to access the dashboard page\n    So that I can view my account information and data",
    "keyword": "Feature",
    "name": "OrgUploadAssets Page Functionality",
    "line": 1,
    "id": "orguploadassets-page-functionality",
    "tags": [],
    "uri": "OrgUploadAssets.feature",
    "elements": [
      {
        "id": "orguploadassets-page-functionality;add-asset,-search,-edit-and-delete-asset",
        "keyword": "Scenario",
        "line": 13,
        "name": "Add Asset, Search, Edit and Delete Asset",
        "tags": [],
        "type": "scenario",
        "steps": [
          {
            "arguments": [],
            "keyword": "Given ",
            "line": 7,
            "name": "I should navigate to application",
            "result": {
              "status": "passed",
              "duration": 2071000000
            }
          },
          {
            "arguments": [],
            "keyword": "When ",
            "line": 8,
            "name": "I should Sign In into the application",
            "result": {
              "status": "passed",
              "duration": 11818000000
            }
          },
          {
            "arguments": [],
            "keyword": "Then ",
            "line": 9,
            "name": "close the terms of service window",
            "result": {
              "status": "passed",
              "duration": 9072000000
            }
          },
          {
            "arguments": [],
            "keyword": "Then ",
            "line": 10,
            "name": "Click on Manage Devices",
            "result": {
              "status": "passed",
              "duration": 76000000
            }
          },
          {
            "arguments": [],
            "keyword": "And ",
            "line": 11,
            "name": "Click on OrgUploadAssets Tab",
            "result": {
              "status": "passed",
              "duration": 979000000
            }
          },
          {
            "arguments": [],
            "keyword": "And ",
            "line": 14,
            "name": "Verify the Title of OrgUploadAssets Page",
            "result": {
              "status": "passed",
              "duration": 13000000
            }
          },
          {
            "arguments": [],
            "keyword": "Then ",
            "line": 15,
            "name": "Filters of OrgUploadAssets should be visible",
            "result": {
              "status": "passed",
              "duration": 6000000
            }
          },
          {
            "arguments": [],
            "keyword": "And ",
            "line": 16,
            "name": "Table for OrgUploadAssets should be visible",
            "result": {
              "status": "passed",
              "duration": 7000000
            }
          },
          {
            "arguments": [],
            "keyword": "Then ",
            "line": 17,
            "name": "I should click on Add Asset",
            "result": {
              "status": "passed",
              "duration": 68000000
            }
          },
          {
            "arguments": [],
            "keyword": "Then ",
            "line": 18,
            "name": "Enter title, full name location and tag",
            "result": {
              "status": "passed",
              "duration": 405000000
            }
          },
          {
            "arguments": [],
            "keyword": "And ",
            "line": 19,
            "name": "Enter note, Type and description",
            "result": {
              "status": "passed",
              "duration": 515000000
            }
          },
          {
            "arguments": [],
            "keyword": "Then ",
            "line": 20,
            "name": "Upload the image file",
            "result": {
              "status": "passed",
              "duration": 467000000
            }
          },
          {
            "arguments": [],
            "keyword": "And ",
            "line": 21,
            "name": "Click on save button",
            "result": {
              "status": "passed",
              "duration": 71000000
            }
          },
          {
            "arguments": [],
            "keyword": "Then ",
            "line": 22,
            "name": "Verify the asset details added in table",
            "result": {
              "status": "failed",
              "duration": 30244000000,
              "error_message": "AssertionError: Timed out retrying after 30000ms: Expected to find element: `.MuiAlert-message`, but never found it.\n    at OrgUploadAssetsActions.verifyRecordTable (cypress/integration/PageObject/PageActions/OrgUploadAssetsActions.js:62:30)\n    at Context.eval (cypress/integration/OrgUploadAssets/OrgUploadAssets.spec.js:56:8)\n    at Context.resolveAndRunStepDefinition (node_modules/cypress-cucumber-preprocessor/lib/resolveStepDefinition.js:193:0)\n    at Context.eval (node_modules/cypress-cucumber-preprocessor/lib/createTestFromScenario.js:27:0)"
            }
          },
          {
            "arguments": [],
            "keyword": "And ",
            "line": 23,
            "name": "Enter the title in search box",
            "result": {
              "status": "skipped"
            }
          },
          {
            "arguments": [],
            "keyword": "And ",
            "line": 24,
            "name": "Verify the record in searching history",
            "result": {
              "status": "skipped"
            }
          },
          {
            "arguments": [],
            "keyword": "And ",
            "line": 25,
            "name": "Click on Edit button",
            "result": {
              "status": "skipped"
            }
          },
          {
            "arguments": [],
            "keyword": "Then ",
            "line": 26,
            "name": "I should edit title, full name location and tag",
            "result": {
              "status": "skipped"
            }
          },
          {
            "arguments": [],
            "keyword": "And ",
            "line": 27,
            "name": "I should edit note, Type and description",
            "result": {
              "status": "skipped"
            }
          },
          {
            "arguments": [],
            "keyword": "Then ",
            "line": 28,
            "name": "ReUpload the image file",
            "result": {
              "status": "skipped"
            }
          },
          {
            "arguments": [],
            "keyword": "Then ",
            "line": 29,
            "name": "Click on save button",
            "result": {
              "status": "skipped"
            }
          },
          {
            "arguments": [],
            "keyword": "And ",
            "line": 30,
            "name": "Verify the Record has been updated Meassage",
            "result": {
              "status": "skipped"
            }
          },
          {
            "arguments": [],
            "keyword": "And ",
            "line": 31,
            "name": "Click on Delete button",
            "result": {
              "status": "skipped"
            }
          },
          {
            "arguments": [],
            "keyword": "Then ",
            "line": 32,
            "name": "Click on Confirm Delete button",
            "result": {
              "status": "skipped"
            }
          },
          {
            "arguments": [],
            "keyword": "And ",
            "line": 33,
            "name": "Verify the record is deleted successfully",
            "result": {
              "status": "skipped"
            }
          }
        ]
      }
    ]
  }
]