[
  {
    "description": "  As a user\n  I want to access the dashboard page\n  So that I can view my account information and data",
    "keyword": "Feature",
    "name": "RepairTickets Page Functionality",
    "line": 1,
    "id": "repairtickets-page-functionality",
    "tags": [],
    "uri": "RepairTickets.feature",
    "elements": [
      {
        "id": "repairtickets-page-functionality;visiblity-check-create-a-ticket-download-export,view-and-search-with-all-type",
        "keyword": "Scenario",
        "line": 12,
        "name": "Visiblity check Create a ticket download export,view and search with all type",
        "tags": [],
        "type": "scenario",
        "steps": [
          {
            "arguments": [],
            "keyword": "Given ",
            "line": 7,
            "name": "I should navigate to application",
            "result": {
              "status": "passed",
              "duration": 1129000000
            }
          },
          {
            "arguments": [],
            "keyword": "When ",
            "line": 8,
            "name": "I should Sign In into the application",
            "result": {
              "status": "passed",
              "duration": 6643000000
            }
          },
          {
            "arguments": [],
            "keyword": "Then ",
            "line": 9,
            "name": "close the terms of service window",
            "result": {
              "status": "passed",
              "duration": 12016000000
            }
          },
          {
            "arguments": [],
            "keyword": "Then ",
            "line": 10,
            "name": "Click on Repair360 page",
            "result": {
              "status": "passed",
              "duration": 93000000
            }
          },
          {
            "arguments": [],
            "keyword": "And ",
            "line": 148,
            "name": "Click on Download import button",
            "result": {
              "status": "passed",
              "duration": 3125000000
            }
          },
          {
            "arguments": [],
            "keyword": "Then ",
            "line": 149,
            "name": "Click on Learn More button",
            "result": {
              "status": "passed",
              "duration": 63000000
            }
          },
          {
            "arguments": [],
            "keyword": "And ",
            "line": 150,
            "name": "Verify Dream Data Filtering Guide should be visible",
            "result": {
              "status": "passed",
              "duration": 95000000
            }
          },
          {
            "arguments": [],
            "keyword": "And ",
            "line": 151,
            "name": "Click on view button",
            "result": {
              "status": "passed",
              "duration": 1192000000
            }
          },
          {
            "arguments": [],
            "keyword": "Then ",
            "line": 152,
            "name": "Verify the Details of student repair ticket",
            "result": {
              "status": "passed",
              "duration": 4016000000
            }
          },
          {
            "arguments": [],
            "keyword": "And ",
            "line": 153,
            "name": "Click on Print Ticket Estimate button",
            "result": {
              "status": "passed",
              "duration": 950000000
            }
          },
          {
            "arguments": [],
            "keyword": "Then ",
            "line": 154,
            "name": "Click on Download Ticket Estimate button",
            "result": {
              "status": "passed",
              "duration": 542000000
            }
          },
          {
            "arguments": [],
            "keyword": "Then ",
            "line": 155,
            "name": "Click on Add Repair Image and Verify",
            "result": {
              "status": "passed",
              "duration": 655000000
            }
          },
          {
            "arguments": [],
            "keyword": "And ",
            "line": 156,
            "name": "Click on Add Note and Verify",
            "result": {
              "status": "passed",
              "duration": 1054000000
            }
          }
        ]
      }
    ]
  }
]